setup.py
ScanHost/ScanHost.py
ScanHost/__init__.py
ScanPort/ScanPort.py
ScanPort/__init__.py
ScanRed.egg-info/PKG-INFO
ScanRed.egg-info/SOURCES.txt
ScanRed.egg-info/dependency_links.txt
ScanRed.egg-info/top_level.txt