Metadata-Version: 2.1
Name: ScanRed
Version: 1.0.0
Summary: Escanea las redes y puertos
Home-page: 
Author: Daniel Rodolfo Herr
Author-email: dherr.ar@gmail.com
